reorient_nii.py
reorient_nii-1.0.0.dist-info/LICENSE
reorient_nii-1.0.0.dist-info/WHEEL
reorient_nii-1.0.0.dist-info/METADATA
reorient_nii-1.0.0.dist-info/RECORD
