Metadata-Version: 2.1
Name: reorient-nii
Version: 1.0.0
Summary: Load and reorient nifti images
Home-page: https://github.com/aptinis/reorient-nii
License: Apache-2.0
Author: aptinis
Author-email: 8akp1@queensu.ca
Requires-Python: >=3.8,<4.0
Classifier: License :: OSI Approved :: Apache Software License
Classifier: Programming Language :: Python :: 3
Classifier: Programming Language :: Python :: 3.10
Classifier: Programming Language :: Python :: 3.8
Classifier: Programming Language :: Python :: 3.9
Requires-Dist: nibabel (>=3.2.2,<4.0.0)
Project-URL: Documentation, https://github.com/aptinis/reorient-nii
Project-URL: Repository, https://github.com/aptinis/reorient-nii
